nb_cli_plugin_littlepaimon/__init__.py
nb_cli_plugin_littlepaimon/cli.py
nb_cli_plugin_littlepaimon/commands/__init__.py
nb_cli_plugin_littlepaimon/commands/create.py
nb_cli_plugin_littlepaimon/commands/install.py
nb_cli_plugin_littlepaimon/commands/resources.py
nb_cli_plugin_littlepaimon/commands/run.py
nb_cli_plugin_littlepaimon/commands/update.py
nb_cli_plugin_littlepaimon/config_template.yml
nb_cli_plugin_littlepaimon/handlers/__init__.py
nb_cli_plugin_littlepaimon/handlers/cmd.py
nb_cli_plugin_littlepaimon/handlers/download.py
nb_cli_plugin_littlepaimon/handlers/gocq.py
nb_cli_plugin_littlepaimon/meta.py
nb_cli_plugin_littlepaimon/plugin.py
nb_cli_plugin_littlepaimon-1.0.3.dist-info/LICENSE
nb_cli_plugin_littlepaimon-1.0.3.dist-info/METADATA
nb_cli_plugin_littlepaimon-1.0.3.dist-info/WHEEL
nb_cli_plugin_littlepaimon-1.0.3.dist-info/entry_points.txt
nb_cli_plugin_littlepaimon-1.0.3.dist-info/RECORD
