Metadata-Version: 2.1
Name: nb-cli-plugin-littlepaimon
Version: 1.0.3
Summary: Nonebot Cli plugin for LittlePaimon
Home-page: https://github.com/CMHopeSunshine/nb-cli-plugin-littlepaimon
License: AGPL
Keywords: nonebot2,nb-cli
Author: CMHopeSunshine
Author-email: 277073121@qq.com
Requires-Python: >=3.8,<4.0
Classifier: License :: Other/Proprietary License
Classifier: Programming Language :: Python :: 3
Classifier: Programming Language :: Python :: 3.8
Classifier: Programming Language :: Python :: 3.9
Classifier: Programming Language :: Python :: 3.10
Classifier: Programming Language :: Python :: 3.11
Requires-Dist: nb-cli (>=1.0.2,<2.0.0)
Requires-Dist: py-cpuinfo (>=9.0.0,<10.0.0)
Requires-Dist: rich (>=13.3.1,<14.0.0)
